clicking/__init__.py
clicking/style.py
clicking-0.2.0.dist-info/AUTHORS.rst
clicking-0.2.0.dist-info/LICENSE
clicking-0.2.0.dist-info/METADATA
clicking-0.2.0.dist-info/WHEEL
clicking-0.2.0.dist-info/top_level.txt
clicking-0.2.0.dist-info/zip-safe
clicking-0.2.0.dist-info/RECORD
