Metadata-Version: 2.1
Name: clicking
Version: 0.2.0
Summary: Convenience function for Click.
Home-page: https://gitlab.com/julot/clicking
Author: Andy Yulius
Author-email: andy.julot@gmail.com
License: MIT license
Keywords: clicking
Platform: UNKNOWN
Classifier: Development Status :: 2 - Pre-Alpha
Classifier: Intended Audience :: Developers
Classifier: License :: OSI Approved :: MIT License
Classifier: Natural Language :: English
Classifier: Programming Language :: Python :: 2
Classifier: Programming Language :: Python :: 2.7
Classifier: Programming Language :: Python :: 3
Classifier: Programming Language :: Python :: 3.4
Classifier: Programming Language :: Python :: 3.5
Classifier: Programming Language :: Python :: 3.6
Requires-Dist: Click (>=6.0)
Requires-Dist: click-help-colors (>=0.5)
Requires-Dist: colorama (>=0.4.1)
Provides-Extra: dev
Requires-Dist: bumpversion ; extra == 'dev'
Requires-Dist: flake8 ; extra == 'dev'
Requires-Dist: pip-review ; extra == 'dev'
Requires-Dist: rope ; extra == 'dev'
Requires-Dist: twine ; extra == 'dev'
